babygrad6/__init__.py
babygrad6/docs.py
babygrad6/graph.py
babygrad6/io.py
babygrad6/tree.py
babygrad6-1.0.0.dist-info/METADATA
babygrad6-1.0.0.dist-info/WHEEL
babygrad6-1.0.0.dist-info/top_level.txt
babygrad6-1.0.0.dist-info/RECORD
