Metadata-Version: 2.4
Name: babygrad6
Version: 1.0.0
Summary: A dynamic library for competitive programming with tree and graph algorithms
Author-email: Your Name <your.email@example.com>
License: MIT
Classifier: Programming Language :: Python :: 3
Classifier: Operating System :: OS Independent
Requires-Python: >=3.6
Requires-Dist: networkx
